ucas_dm/__init__.py
ucas_dm/utils.py
ucas_dm/prediction_algorithms/__init__.py
ucas_dm/prediction_algorithms/base_algo.py
ucas_dm/prediction_algorithms/baseline.py
ucas_dm/prediction_algorithms/collaborate_based_algo.py
ucas_dm/prediction_algorithms/content_based_algo.py
ucas_dm/prediction_algorithms/nmf.py
ucas_dm/prediction_algorithms/surprise_base_algo.py
ucas_dm/prediction_algorithms/topic_based_algo.py
ucas_dm/preprocess/__init__.py
ucas_dm/preprocess/preprocess.py
ucas_dm-1.0.1.data/data/ucas_dm/preprocess/stop_words/stop.txt
ucas_dm-1.0.1.dist-info/METADATA
ucas_dm-1.0.1.dist-info/RECORD
ucas_dm-1.0.1.dist-info/WHEEL
ucas_dm-1.0.1.dist-info/top_level.txt
